bitpanda/BitpandaClient.py
bitpanda/Pair.py
bitpanda/Timer.py
bitpanda/__init__.py
bitpanda/enums.py
bitpanda/subscriptions.py
bitpanda_aio-2.0.2.dist-info/LICENSE
bitpanda_aio-2.0.2.dist-info/METADATA
bitpanda_aio-2.0.2.dist-info/WHEEL
bitpanda_aio-2.0.2.dist-info/top_level.txt
bitpanda_aio-2.0.2.dist-info/RECORD
