Metadata-Version: 2.1
Name: bitpanda-aio
Version: 2.0.2
Summary: Bitpanda Global Exchange API asynchronous python client
Home-page: https://github.com/nardew/bitpanda-aio
Author: nardew
Author-email: bitpanda.aio@gmail.com
License: UNKNOWN
Platform: UNKNOWN
Classifier: Development Status :: 5 - Production/Stable
Classifier: Framework :: AsyncIO
Classifier: Intended Audience :: Developers
Classifier: Programming Language :: Python :: 3
Classifier: Programming Language :: Python :: 3.6
Classifier: Programming Language :: Python :: 3.7
Classifier: License :: OSI Approved :: MIT License
Classifier: Operating System :: OS Independent
Classifier: Topic :: Software Development :: Libraries
Classifier: Topic :: Software Development :: Libraries :: Python Modules
Classifier: Typing :: Typed
Requires-Python: >=3.6
Requires-Dist: aiohttp (==3.6.2)
Requires-Dist: websockets (==8.1)
Requires-Dist: pytz (==2019.3)
